braintracer/__init__.py
braintracer/analysis.py
braintracer/anterograde_pipeline.ipynb
braintracer/area_lists.py
braintracer/area_projections.ipynb
braintracer/bt.bat
braintracer/bt.sh
braintracer/bt_visualiser.ipynb
braintracer/file_management.py
braintracer/plotting.py
braintracer/plotting_helpers.py
braintracer/sample_data/cells_SC014_bt14_r.csv
braintracer/sample_data/cells_SC015_bt14_r.csv
braintracer/sample_data/cells_SC016_bt14_r.csv
braintracer/sample_data/cells_SC017_bt14_r.csv
braintracer-0.4.1.dist-info/licenses/LICENSE.txt
braintracer-0.4.1.dist-info/METADATA
braintracer-0.4.1.dist-info/WHEEL
braintracer-0.4.1.dist-info/top_level.txt
braintracer-0.4.1.dist-info/RECORD
