Metadata-Version: 2.4
Name: braintracer
Version: 0.4.1
Summary: A complete processing pipeline for anatomical neuronal tracing.
Home-page: https://github.com/samclothier/braintracer
Download-URL: https://github.com/samclothier/braintracer/archive/refs/tags/0.4.1.tar.gz
Author: Sam Clothier
Author-email: sam.clothier.18@ucl.ac.uk
Keywords: neuroscience,tracing,anatomy,brainglobe,cellfinder,brainreg
Classifier: Development Status :: 3 - Alpha
Classifier: Programming Language :: Python :: 3
Classifier: Programming Language :: Python :: 3.11
Classifier: Operating System :: Microsoft :: Windows
Classifier: Framework :: Jupyter :: JupyterLab
Classifier: Framework :: Matplotlib
Classifier: License :: OSI Approved :: GNU General Public License v3 (GPLv3)
Classifier: Intended Audience :: Science/Research
Classifier: Topic :: Scientific/Engineering :: Image Recognition
Classifier: Natural Language :: English
Requires-Python: >=3.11
License-File: LICENSE.txt
Requires-Dist: brainglobe>=1.3
Requires-Dist: brainglobe-workflows>=1.4
Requires-Dist: jupyterlab>=4.4
Requires-Dist: opencv-python>=4.6.0.66
Requires-Dist: plotly>=5.10.0
Requires-Dist: fastcluster>=1.2.0
Requires-Dist: shortuuid>=1.0.9
Requires-Dist: statsmodels>=0.13
Requires-Dist: ipyvtklink>=0.2
Requires-Dist: PyMCubes>=0.1.6
Requires-Dist: read-roi>=1.6.0
Dynamic: download-url
Dynamic: license-file
